rscheduler-0.2.1.dist-info/METADATA
rscheduler-0.2.1.dist-info/WHEEL
rscheduler-0.2.1.dist-info/licenses/LICENSE
rscheduler.libs/libgcc_s-e52197c3.so.1
rscheduler/__init__.py
rscheduler/rscheduler.cpython-313t-aarch64-linux-musl.so
rscheduler-0.2.1.dist-info/RECORD
