Metadata-Version: 2.4
Name: rscheduler
Version: 0.2.1
Classifier: Programming Language :: Rust
Classifier: Programming Language :: Python :: Implementation :: CPython
Classifier: Programming Language :: Python :: Implementation :: PyPy
License-File: LICENSE
Summary: A high-precision task scheduler for Python, built with Rust for accuracy and efficiency
Author: Takahiro Ishiguro
License: Apache-2.0
Requires-Python: >=3.8
Project-URL: Source Code, https://github.com/LemonPepperSeasoning/rscheduler
